irisml/tasks/create_azure_customvision_docker_model.py
irisml/tasks/create_azure_customvision_model.py
irisml/tasks/create_azure_customvision_project.py
irisml/tasks/delete_azure_customvision_project.py
irisml/tasks/export_azure_customvision_model.py
irisml/tasks/train_azure_customvision_project.py
irisml_tasks_azure_customvision-0.0.1.dist-info/LICENSE
irisml_tasks_azure_customvision-0.0.1.dist-info/METADATA
irisml_tasks_azure_customvision-0.0.1.dist-info/WHEEL
irisml_tasks_azure_customvision-0.0.1.dist-info/top_level.txt
irisml_tasks_azure_customvision-0.0.1.dist-info/RECORD
