Metadata-Version: 2.1
Name: irisml-tasks-azure-customvision
Version: 0.0.1
Summary: Azure Custom Vision API tasks for IrisML
Home-page: https://github.com/microsoft/irisml-tasks-azure-customvision
Author: irisdev
License: MIT
Requires-Python: >=3.8
License-File: LICENSE
Requires-Dist: irisml
Requires-Dist: Pillow
Requires-Dist: requests
Requires-Dist: tenacity
